Sloppy/api.py
Sloppy/common.py
Sloppy/config.py
Sloppy/database.py
Sloppy/datetime.py
Sloppy/error.py
Sloppy/excel.py
Sloppy/json.py
Sloppy/log.py
Sloppy/message.py
Sloppy/remote.py
Sloppy/security.py
Sloppy-0.0.0.0.0.0.0.31.dist-info/METADATA
Sloppy-0.0.0.0.0.0.0.31.dist-info/WHEEL
Sloppy-0.0.0.0.0.0.0.31.dist-info/top_level.txt
Sloppy-0.0.0.0.0.0.0.31.dist-info/RECORD
